sc_utils/README.md
sc_utils/__init__.py
sc_utils/network.py
sc_utils/scanpy_utils.py
snrnatools-0.3.1.dist-info/METADATA
snrnatools-0.3.1.dist-info/WHEEL
snrnatools-0.3.1.dist-info/RECORD
