Metadata-Version: 2.4
Name: snRNAtools
Version: 0.3.1
Summary: A Python package utils to support scanpy usage and enrichment and network analysis given gene list
Project-URL: Homepage, https://github.com/brainfo/snRNAtools
Project-URL: Issues, https://github.com/brainfo/snRNAtools/issues
Author-email: brainfo <scilavisher@gmail.com>
Classifier: License :: OSI Approved :: MIT License
Classifier: Operating System :: OS Independent
Classifier: Programming Language :: Python :: 3
Requires-Python: >=3.8
